vemomoto_core/__init__.pxd
vemomoto_core/npcollections/FixedOrderedIntDict.cp311-win_amd64.pyd
vemomoto_core/npcollections/FixedOrderedIntDict.cpp
vemomoto_core/npcollections/FixedOrderedIntDict.pxd
vemomoto_core/npcollections/FixedOrderedIntDict.pyx
vemomoto_core/npcollections/_FixedOrderedIntDict_reduce.py
vemomoto_core/npcollections/__init__.py
vemomoto_core/npcollections/_npextc_utils.py
vemomoto_core/npcollections/_setup_FixedOrderedIntDict.py
vemomoto_core/npcollections/_setup_intquickheapdict.py
vemomoto_core/npcollections/_setup_npextc.py
vemomoto_core/npcollections/heapoperations_c.c
vemomoto_core/npcollections/intquickheapdict.cp311-win_amd64.pyd
vemomoto_core/npcollections/intquickheapdict.cpp
vemomoto_core/npcollections/intquickheapdict.pxd
vemomoto_core/npcollections/intquickheapdict.pyx
vemomoto_core/npcollections/npext.py
vemomoto_core/npcollections/npextc.cp311-win_amd64.pyd
vemomoto_core/npcollections/npextc.cpp
vemomoto_core/npcollections/npextc.pxd
vemomoto_core/npcollections/npextc.pyx
vemomoto_core/npcollections/sectionsum.c
vemomoto_core/npcollections/sparse3d.py
vemomoto_core_npcollections-0.9.0a12.dist-info/LICENSE
vemomoto_core_npcollections-0.9.0a12.dist-info/METADATA
vemomoto_core_npcollections-0.9.0a12.dist-info/WHEEL
vemomoto_core_npcollections-0.9.0a12.dist-info/top_level.txt
vemomoto_core_npcollections-0.9.0a12.dist-info/RECORD
