Metadata-Version: 2.1
Name: vemomoto-core-npcollections
Version: 0.9.0a12
Summary: Flexible containers based on numpy arrays
Home-page: https://github.com/vemomoto/vemomoto
Author: Samuel M. Fischer
License: LGPLv3
Project-URL: Bug Tracker, https://github.com/vemomoto/vemomoto/issues
Project-URL: Documentation, https://vemomoto.github.io/vemomoto_core/vemomoto_core.npcollections
Project-URL: Source Code, https://github.com/vemomoto/vemomoto/tree/master/vemomoto_core/vemomoto_core_npcollections
Keywords: numpy,array,container,heap,dictionary
Classifier: License :: OSI Approved :: GNU Lesser General Public License v3 (LGPLv3)
Classifier: Development Status :: 3 - Alpha
Classifier: Intended Audience :: Developers
Requires-Python: >=3.6
License-File: LICENSE
Requires-Dist: numpy
Requires-Dist: scipy
Requires-Dist: vemomoto-core-tools
Requires-Dist: cython
